README.md
pyproject.toml
setup.cfg
setup.py
fso_sdd_demo/__init__.py
fso_sdd_demo/client.py
fso_sdd_demo.egg-info/PKG-INFO
fso_sdd_demo.egg-info/SOURCES.txt
fso_sdd_demo.egg-info/dependency_links.txt
fso_sdd_demo.egg-info/requires.txt
fso_sdd_demo.egg-info/top_level.txt